computenestcli/__init__.py
computenestcli/base_log.py
computenestcli/log.conf
computenestcli/main.py
computenestcli/process_config.yaml
computenestcli/client/__init__.py
computenestcli/client/base.py
computenestcli/client/computenest.py
computenestcli/client/ecs.py
computenestcli/client/oos.py
computenestcli/common/__init__.py
computenestcli/common/arch.py
computenestcli/common/artifact_processor_helper.py
computenestcli/common/artifact_source_type.py
computenestcli/common/constant.py
computenestcli/common/context.py
computenestcli/common/credentials.py
computenestcli/common/decorator.py
computenestcli/common/delivery_type.py
computenestcli/common/docker_compose_helper.py
computenestcli/common/export_type.py
computenestcli/common/file_util.py
computenestcli/common/locale.py
computenestcli/common/logging_constant.py
computenestcli/common/logging_type.py
computenestcli/common/project_setup_constant.py
computenestcli/common/service_processor_helper.py
computenestcli/common/service_type.py
computenestcli/common/str_util.py
computenestcli/common/terraform_util.py
computenestcli/common/upload_file_type.py
computenestcli/common/util.py
computenestcli/exception/__init__.py
computenestcli/exception/cli_common_exception.py
computenestcli/exception/global_exception_handler.py
computenestcli/processor/__init__.py
computenestcli/processor/artifact.py
computenestcli/processor/check.py
computenestcli/processor/image.py
computenestcli/processor/jinja2.py
computenestcli/processor/service.py
computenestcli/processor/deliver_image/__init__.py
computenestcli/processor/deliver_image/deliver_image_manager.py
computenestcli/processor/deliver_image/impl/__init__.py
computenestcli/processor/deliver_image/impl/base.py
computenestcli/processor/deliver_image/impl/docker_compose.py
computenestcli/processor/deliver_image/impl/helm_chart.py
computenestcli/resources/supported_projects.yaml
computenestcli/resources/project_generation/README.md
computenest_cli-1.9.6.dist-info/METADATA
computenest_cli-1.9.6.dist-info/WHEEL
computenest_cli-1.9.6.dist-info/entry_points.txt
computenest_cli-1.9.6.dist-info/top_level.txt
computenest_cli-1.9.6.dist-info/RECORD
